dexterity.localroles-2.0.0b0-py3.13-nspkg.pth
dexterity/localroles/__init__.py
dexterity/localroles/adapter.py
dexterity/localroles/configure.zcml
dexterity/localroles/interfaces.py
dexterity/localroles/profiles.zcml
dexterity/localroles/subscriber.py
dexterity/localroles/subscribers.zcml
dexterity/localroles/testing.py
dexterity/localroles/testing.zcml
dexterity/localroles/utility.py
dexterity/localroles/utils.py
dexterity/localroles/vocabulary.py
dexterity/localroles/browser/__init__.py
dexterity/localroles/browser/configure.zcml
dexterity/localroles/browser/exceptions.py
dexterity/localroles/browser/interfaces.py
dexterity/localroles/browser/overrides.py
dexterity/localroles/browser/settings.py
dexterity/localroles/browser/templates/role-config.pt
dexterity/localroles/browser/tests/__init__.py
dexterity/localroles/browser/tests/test_settings.py
dexterity/localroles/locales/dexterity.localroles-generated.pot
dexterity/localroles/locales/dexterity.localroles-manual.pot
dexterity/localroles/locales/dexterity.localroles.pot
dexterity/localroles/locales/en/LC_MESSAGES/dexterity.localroles.po
dexterity/localroles/locales/fr/LC_MESSAGES/dexterity.localroles.po
dexterity/localroles/profiles/plone4/browserlayer.xml
dexterity/localroles/profiles/plone4/cssregistry.xml
dexterity/localroles/profiles/plone4/metadata.xml
dexterity/localroles/profiles/plone6/browserlayer.xml
dexterity/localroles/profiles/plone6/metadata.xml
dexterity/localroles/profiles/plone6/registry.xml
dexterity/localroles/profiles/testing/metadata.xml
dexterity/localroles/profiles/testing/types.xml
dexterity/localroles/profiles/testing/workflows.xml
dexterity/localroles/profiles/testing/types/testingtype.xml
dexterity/localroles/profiles/uninstall/browserlayer.xml
dexterity/localroles/profiles/uninstall/registry.xml
dexterity/localroles/static/settings.css
dexterity/localroles/tests/__init__.py
dexterity/localroles/tests/settings.robot
dexterity/localroles/tests/test_adapter.py
dexterity_localroles-2.0.0b0.dist-info/METADATA
dexterity_localroles-2.0.0b0.dist-info/WHEEL
dexterity_localroles-2.0.0b0.dist-info/namespace_packages.txt
dexterity_localroles-2.0.0b0.dist-info/top_level.txt
dexterity_localroles-2.0.0b0.dist-info/RECORD
