Metadata-Version: 2.4
Name: dexterity.localroles
Version: 2.0.0b0
Summary: Define local roles settings by dexterity type
Home-page: https://github.com/collective/dexterity.localroles
Author: IMIO
Author-email: support@imio.be
License: gpl
Project-URL: PyPI, https://pypi.python.org/pypi/dexterity.localroles
Project-URL: Source, https://github.com/collective/dexterity.localroles
Keywords: Plone Python
Classifier: Environment :: Web Environment
Classifier: Framework :: Plone
Classifier: Framework :: Plone :: 4.3
Classifier: Framework :: Plone :: 5.1
Classifier: Framework :: Plone :: 6.0
Classifier: Framework :: Plone :: 6.1
Classifier: Operating System :: OS Independent
Classifier: Programming Language :: Python
Classifier: Programming Language :: Python :: 2.7
Classifier: Programming Language :: Python :: 3.10
Classifier: Programming Language :: Python :: 3.13
Classifier: Topic :: Software Development :: Libraries :: Python Modules
Requires-Dist: Plone
Requires-Dist: plone.api
Requires-Dist: borg.localrole
Requires-Dist: collective.z3cform.datagridfield
Requires-Dist: plone.app.dexterity
Requires-Dist: setuptools
Requires-Dist: imio.helpers
Provides-Extra: test
Requires-Dist: plone.app.robotframework; extra == "test"
Requires-Dist: plone.app.testing; extra == "test"
Requires-Dist: ecreall.helpers.testing; extra == "test"
Requires-Dist: robotsuite; extra == "test"
Dynamic: author
Dynamic: author-email
Dynamic: classifier
Dynamic: description
Dynamic: home-page
Dynamic: keywords
Dynamic: license
Dynamic: project-url
Dynamic: provides-extra
Dynamic: requires-dist
Dynamic: summary
